django_dynamic_paginator/__init__.py
django_dynamic_paginator/exceptions.py
django_dynamic_paginator/paginator.py
django_dynamic_paginator/utils.py
django_dynamic_paginator-1.1.9.dist-info/licenses/LICENSE
django_dynamic_paginator-1.1.9.dist-info/METADATA
django_dynamic_paginator-1.1.9.dist-info/WHEEL
django_dynamic_paginator-1.1.9.dist-info/top_level.txt
django_dynamic_paginator-1.1.9.dist-info/RECORD
