Metadata-Version: 2.4
Name: django-dynamic-paginator
Version: 1.1.9
Summary: Paginador dinámico avanzado para Django REST Framework con optimizaciones automáticas
Home-page: https://github.com/tuusuario/django-dynamic-paginator
Author: Jorge Luis de la Cruz
Author-email: Jorge Luis de la Cruz <jorgeluisdcl30@gmail.com>
License: MIT
Project-URL: Homepage, https://github.com/tuusuario/django-dynamic-paginator
Project-URL: Repository, https://github.com/tuusuario/django-dynamic-paginator
Project-URL: Issues, https://github.com/tuusuario/django-dynamic-paginator/issues
Project-URL: Documentation, https://github.com/tuusuario/django-dynamic-paginator#readme
Keywords: django,djangorestframework,pagination,dynamic,filtering,optimization
Classifier: Development Status :: 4 - Beta
Classifier: Intended Audience :: Developers
Classifier: License :: OSI Approved :: MIT License
Classifier: Operating System :: OS Independent
Classifier: Programming Language :: Python :: 3
Classifier: Programming Language :: Python :: 3.8
Classifier: Programming Language :: Python :: 3.9
Classifier: Programming Language :: Python :: 3.10
Classifier: Programming Language :: Python :: 3.11
Classifier: Framework :: Django
Classifier: Framework :: Django :: 3.2
Classifier: Framework :: Django :: 4.0
Classifier: Framework :: Django :: 4.1
Classifier: Framework :: Django :: 4.2
Requires-Python: >=3.8
License-File: LICENSE
Requires-Dist: Django>=3.2
Requires-Dist: djangorestframework>=3.12.0
Provides-Extra: dev
Requires-Dist: pytest>=7.0; extra == "dev"
Requires-Dist: pytest-django>=4.5; extra == "dev"
Requires-Dist: black>=22.0; extra == "dev"
Requires-Dist: flake8>=5.0; extra == "dev"
Requires-Dist: mypy>=0.991; extra == "dev"
Provides-Extra: test
Requires-Dist: pytest>=7.0; extra == "test"
Requires-Dist: pytest-django>=4.5; extra == "test"
Requires-Dist: coverage>=6.0; extra == "test"
Dynamic: author
Dynamic: home-page
Dynamic: license-file
Dynamic: requires-python
